fireopal/__init__.py
fireopal/_event_tracker.py
fireopal/_payload.py
fireopal/_utils.py
fireopal/admin.py
fireopal/config.py
fireopal/constants.py
fireopal/credentials/__init__.py
fireopal/credentials/_credentials.py
fireopal/fire_opal_job.py
fireopal/functions/__init__.py
fireopal/functions/_expectation_utils.py
fireopal/functions/_utils.py
fireopal/functions/activity_monitor.py
fireopal/functions/authenticate.py
fireopal/functions/base.py
fireopal/functions/estimate_expectation.py
fireopal/functions/execute.py
fireopal/functions/get_result.py
fireopal/functions/iterate.py
fireopal/functions/iterate_expectation.py
fireopal/functions/read_data.py
fireopal/functions/show_supported_devices.py
fireopal/functions/solve_qaoa.py
fireopal/functions/stop_iterate.py
fireopal/functions/validate.py
fireopal/run_options/__init__.py
fireopal/types/__init__.py
fire_opal-9.2.0.dist-info/LICENSE
fire_opal-9.2.0.dist-info/METADATA
fire_opal-9.2.0.dist-info/WHEEL
fire_opal-9.2.0.dist-info/RECORD
