Metadata-Version: 2.3
Name: fire-opal
Version: 9.2.0
Summary: Fire Opal Client
License: https://q-ctrl.com/terms
Keywords: black opal,boulder opal,fire opal,nisq,open controls,q control,q ctrl,q-control,q-ctrl,qcontrol,qctrl,quantum,quantum algorithms,quantum circuits,quantum coding,quantum coding software,quantum computing,quantum control,quantum control software,quantum control theory,quantum engineering,quantum error correction,quantum firmware,quantum fundamentals,quantum sensing,qubit,qudit
Author: Q-CTRL
Author-email: support@q-ctrl.com
Maintainer: Q-CTRL
Maintainer-email: support@q-ctrl.com
Requires-Python: >=3.9,<3.13
Classifier: Development Status :: 5 - Production/Stable
Classifier: Environment :: Console
Classifier: Intended Audience :: Developers
Classifier: Intended Audience :: Education
Classifier: Intended Audience :: Science/Research
Classifier: Natural Language :: English
Classifier: Operating System :: OS Independent
Classifier: Programming Language :: Python :: 3.9
Classifier: Programming Language :: Python :: 3.10
Classifier: Programming Language :: Python :: 3.11
Classifier: Programming Language :: Python :: 3.12
Classifier: Topic :: Internet :: WWW/HTTP
Classifier: Topic :: Scientific/Engineering :: Physics
Classifier: Topic :: Scientific/Engineering :: Visualization
Classifier: Topic :: Software Development :: Embedded Systems
Classifier: Topic :: System :: Distributed Computing
Requires-Dist: qctrl-client (>=14.0.0,<15.0.0)
Requires-Dist: qctrl-commons (>=25.1.2,<26.0.0)
Requires-Dist: qctrl-workflow-client (>=7.3.0,<8.0.0)
Requires-Dist: segment-analytics-python (>=2.2.2,<3.0.0)
Project-URL: Facebook, https://www.facebook.com/qctrl
Project-URL: GitHub, https://github.com/qctrl
Project-URL: LinkedIn, https://www.linkedin.com/company/q-ctrl/
Project-URL: X, https://x.com/qctrlHQ
Project-URL: YouTube, https://www.youtube.com/qctrl
